torchegranate/__init__.py
torchegranate/_base.py
torchegranate/_bayes.py
torchegranate/_dense_hmm.py
torchegranate/_sparse_hmm.py
torchegranate/_utils.py
torchegranate/bayes_classifier.py
torchegranate/bayesian_network.py
torchegranate/dense_hmm.py
torchegranate/factor_graph.py
torchegranate/gmm.py
torchegranate/hmm.py
torchegranate/kmeans.py
torchegranate/markov_chain.py
torchegranate/sparse_hmm.py
torchegranate/distributions/ConditionalCategorical.py
torchegranate/distributions/JointCategorical.py
torchegranate/distributions/__init__.py
torchegranate/distributions/_distribution.py
torchegranate/distributions/bernoulli.py
torchegranate/distributions/categorical.py
torchegranate/distributions/conditional_categorical.py
torchegranate/distributions/dirac_delta.py
torchegranate/distributions/exponential.py
torchegranate/distributions/gamma.py
torchegranate/distributions/independent_components.py
torchegranate/distributions/joint_categorical.py
torchegranate/distributions/lognormal.py
torchegranate/distributions/negative_binomial.py
torchegranate/distributions/normal.py
torchegranate/distributions/poisson.py
torchegranate/distributions/student_t.py
torchegranate/distributions/uniform.py
torchegranate/distributions/zero_inflated.py
torchegranate/hmm/__init__.py
torchegranate/hmm/_base.py
torchegranate/hmm/dense_hmm.py
torchegranate/hmm/sparse_hmm.py
torchegranate-0.5.0.dist-info/LICENSE
torchegranate-0.5.0.dist-info/METADATA
torchegranate-0.5.0.dist-info/WHEEL
torchegranate-0.5.0.dist-info/top_level.txt
torchegranate-0.5.0.dist-info/RECORD
