Metadata-Version: 2.1
Name: torchegranate
Version: 0.5.0
Summary: A rewrite of pomegranate using PyTorch.
Home-page: https://github.com/jmschrei/torchegranate
Author: Jacob Schreiber
Author-email: jmschreiber91@gmail.com
License: LICENSE.txt
License-File: LICENSE
Requires-Dist: numpy (>=1.22.2)
Requires-Dist: scipy (>=1.6.2)
Requires-Dist: scikit-learn (>=1.0.2)
Requires-Dist: torch (>=1.9.0)
Requires-Dist: apricot-select (>=0.6.1)
Requires-Dist: networkx (>=2.8.4)
